cldk/__init__.py
cldk/analysis/__init__.py
cldk/analysis/c/__init__.py
cldk/analysis/c/c_analysis.py
cldk/analysis/c/clang/__init__.py
cldk/analysis/c/clang/clang_analyzer.py
cldk/analysis/commons/__init__.py
cldk/analysis/commons/lsp/__init__.py
cldk/analysis/commons/lsp/lsp.py
cldk/analysis/commons/treesitter/__init__.py
cldk/analysis/commons/treesitter/models.py
cldk/analysis/commons/treesitter/treesitter_java.py
cldk/analysis/commons/treesitter/treesitter_python.py
cldk/analysis/commons/treesitter/utils/__init__.py
cldk/analysis/commons/treesitter/utils/treesitter_utils.py
cldk/analysis/java/__init__.py
cldk/analysis/java/codeanalyzer/__init__.py
cldk/analysis/java/codeanalyzer/codeanalyzer.py
cldk/analysis/java/codeanalyzer/jar/.gitignore
cldk/analysis/java/codeanalyzer/jar/__init__.py
cldk/analysis/java/codeanalyzer/jar/codeanalyzer-2.3.5.jar
cldk/analysis/java/java_analysis.py
cldk/analysis/python/__init__.py
cldk/analysis/python/python_analysis.py
cldk/core.py
cldk/models/__init__.py
cldk/models/c/__init__.py
cldk/models/c/models.py
cldk/models/java/__init__.py
cldk/models/java/enums.py
cldk/models/java/models.py
cldk/models/python/__init__.py
cldk/models/python/models.py
cldk/models/treesitter/__init__.py
cldk/utils/__init__.py
cldk/utils/exceptions/__init__.py
cldk/utils/exceptions/exceptions.py
cldk/utils/logging.py
cldk/utils/sanitization/__init__.py
cldk/utils/sanitization/java/__init__.py
cldk/utils/sanitization/java/treesitter_sanitizer.py
cldk/utils/sanitization/java/treesitter_utils.py
cldk-1.0.6.dist-info/LICENSE
cldk-1.0.6.dist-info/METADATA
cldk-1.0.6.dist-info/WHEEL
cldk-1.0.6.dist-info/RECORD
