Metadata-Version: 2.3
Name: cldk
Version: 1.0.6
Summary: The official Python SDK for Codellm-Devkit.
License: Apache 2.0
Keywords: ibm,llm,large language models,code analyzer,syntax tree
Author: Rahul Krishna
Author-email: i.m.ralk@gmail.com
Requires-Python: >=3.11
Classifier: Development Status :: 4 - Beta
Classifier: Environment :: Console
Classifier: Intended Audience :: Developers
Classifier: License :: OSI Approved :: Apache Software License
Classifier: License :: Other/Proprietary License
Classifier: Operating System :: OS Independent
Classifier: Programming Language :: Python
Classifier: Programming Language :: Python :: 3
Classifier: Programming Language :: Python :: 3.11
Classifier: Programming Language :: Python :: 3.12
Classifier: Programming Language :: Python :: 3.13
Classifier: Topic :: Scientific/Engineering :: Artificial Intelligence
Classifier: Topic :: Software Development :: Libraries :: Application Frameworks
Classifier: Topic :: Software Development :: Libraries :: Python Modules
Requires-Dist: clang (==17.0.6)
Requires-Dist: libclang (==17.0.6)
Requires-Dist: networkx (>=3.4.2,<4.0.0)
Requires-Dist: pandas (>=2.2.3,<3.0.0)
Requires-Dist: pyarrow (==20.0.0)
Requires-Dist: pydantic (>=2.10.6,<3.0.0)
Requires-Dist: requests (>=2.32.3,<3.0.0)
Requires-Dist: rich (==14.0.0)
Requires-Dist: tree-sitter (==0.24.0)
Requires-Dist: tree-sitter-c (==0.23.5)
Requires-Dist: tree-sitter-go (==0.23.4)
Requires-Dist: tree-sitter-java (==0.23.5)
Requires-Dist: tree-sitter-javascript (==0.23.1)
Requires-Dist: tree-sitter-python (==0.23.6)
Requires-Dist: wget (==3.2)
Project-URL: Homepage, https://codellm-devkit.info
Project-URL: Repository, https://github.com/codellm-devkit/python-sdk
